<annotation>
<folder>images</folder>
<filename>f4feb24c-img130.jpg</filename>
<source>
<database>MyDatabase</database>
<annotation>COCO2017</annotation>
<image>flickr</image>
<flickrid>NULL</flickrid>
<annotator>1</annotator>
</source>
<owner>
<flickrid>NULL</flickrid>
<name>Label Studio</name>
</owner>
<size>
<width>488</width>
<height>488</height>
<depth>3</depth>
</size>
<segmented>0</segmented>
<object>
<name>Giant panda</name>
<pose>Unspecified</pose>
<truncated>0</truncated>
<difficult>0</difficult>
<bndbox>
<xmin>79</xmin>
<ymin>146</ymin>
<xmax>192</xmax>
<ymax>257</ymax>
</bndbox>
</object>
<object>
<name>Red panda</name>
<pose>Unspecified</pose>
<truncated>0</truncated>
<difficult>0</difficult>
<bndbox>
<xmin>349</xmin>
<ymin>309</ymin>
<xmax>426</xmax>
<ymax>377</ymax>
</bndbox>
</object>
</annotation>
